coinbase/__init__.py
coinbase/auth.py
coinbase/cli.py
coinbase/const.py
coinbase/mgmt.py
coincli-1.0.0.dist-info/METADATA
coincli-1.0.0.dist-info/WHEEL
coincli-1.0.0.dist-info/entry_points.txt
coincli-1.0.0.dist-info/top_level.txt
coincli-1.0.0.dist-info/RECORD
