Metadata-Version: 2.1
Name: coincli
Version: 1.0.0
Summary: Unofficial Coinbase CLI tools based on Coinbase v2 API
Home-page: https://github.com/arthuRHD/coincli
Author: Arthur RICHARD
Author-email: arthur.richard@protonmail.com
License: UNKNOWN
Platform: UNKNOWN
Classifier: Programming Language :: Python :: 3
Classifier: License :: OSI Approved :: MIT License
Classifier: Operating System :: OS Independent
Requires-Python: >=3.6
Requires-Dist: pipenv
Requires-Dist: pydantic
Requires-Dist: requests
Requires-Dist: setuptools
